chelsa_cmip6/BioClim.py
chelsa_cmip6/GetClim.py
chelsa_cmip6/__init__.py
chelsa_cmip6/run_chelsa_cmip6.py
chelsa_cmip6-1.4.dist-info/LICENSE
chelsa_cmip6-1.4.dist-info/METADATA
chelsa_cmip6-1.4.dist-info/WHEEL
chelsa_cmip6-1.4.dist-info/top_level.txt
chelsa_cmip6-1.4.dist-info/RECORD
