Metadata-Version: 2.1
Name: chelsa_cmip6
Version: 1.4
Summary: This package contains function to create monthly high-resolution climatologies for a selected geographic area for min-, max-, and mean temperature, precipitation rate and bioclimatic variables from anomalies and using CHELSA V2.1 as baseline high resolution climatology. Only works for GCMs for which tas, tasmax, tasmin, and pr are available.
Home-page: https://gitlabext.wsl.ch/karger/chelsa_cmip6.git
Download-URL: https://gitlabext.wsl.ch/karger/chelsa_cmip6/-/archive/v1.0/chelsa_cmip6-v1.0.tar.gz
Author: Dirk Nikolaus Karger
Author-email: dirk.karger@wsl.ch
License: GNU
Project-URL: Bug Tracker, https://github.com/pypa/chelsa_cmip6/issues
Keywords: CMIP6,climate,delta-change,CHELSA,bioclimate,growing degree days,gdd,bio
Classifier: Development Status :: 5 - Production/Stable
Classifier: Intended Audience :: Science/Research
Classifier: Topic :: Scientific/Engineering :: GIS
Requires-Python: >=3.6
License-File: LICENSE
Requires-Dist: numpy
Requires-Dist: xarray
Requires-Dist: pandas
Requires-Dist: zarr
Requires-Dist: gcsfs
Requires-Dist: scipy
Requires-Dist: fsspec
Requires-Dist: dask
Requires-Dist: netcdf4
Requires-Dist: h5netcdf
Requires-Dist: esgf-pyclient
Requires-Dist: siphon
